python_unifi_client/__init__.py
python_unifi_client/client.py
python_unifi_client-1.2.6.dist-info/METADATA
python_unifi_client-1.2.6.dist-info/WHEEL
python_unifi_client-1.2.6.dist-info/top_level.txt
python_unifi_client-1.2.6.dist-info/RECORD
