Metadata-Version: 2.4
Name: python_unifi_client
Version: 1.2.6
Home-page: https://github.com/compdat-llc/unifi-client-python
Author: Michael Lapinski
Author-email: michaellapinski787@gmail.com
Classifier: Programming Language :: Python :: 3
Classifier: License :: OSI Approved :: MIT License
Classifier: Operating System :: OS Independent
Requires-Python: >=3.8, <3.14
Dynamic: author
Dynamic: author-email
Dynamic: classifier
Dynamic: description
Dynamic: description-content-type
Dynamic: home-page
Dynamic: requires-python
